CHANGES.rst
MANIFEST.in
README.rst
setup.py
anybox/__init__.py
anybox.paster.odoo.egg-info/PKG-INFO
anybox.paster.odoo.egg-info/SOURCES.txt
anybox.paster.odoo.egg-info/dependency_links.txt
anybox.paster.odoo.egg-info/entry_points.txt
anybox.paster.odoo.egg-info/namespace_packages.txt
anybox.paster.odoo.egg-info/not-zip-safe
anybox.paster.odoo.egg-info/requires.txt
anybox.paster.odoo.egg-info/top_level.txt
anybox/paster/__init__.py
anybox/paster/odoo/__init__.py
anybox/paster/odoo/instance.py
anybox/paster/odoo/module.py
anybox/paster/odoo/templates/instance/buildout.cfg_tmpl
anybox/paster/odoo/templates/instance/buildout.dev.cfg
anybox/paster/odoo/templates/module/__init__.py_tmpl
anybox/paster/odoo/templates/module/__openerp__.py_tmpl
anybox/paster/odoo/templates/module/i18n/fr.po_tmpl
anybox/paster/odoo/templates/module/security/ir.model.access.csv
anybox/paster/odoo/templates/module/static/description/icon.png
anybox/paster/odoo/templates/module/tests/test.py
anybox/paster/odoo/templates/module/view/menu.xml_tmpl