Metadata-Version: 1.0
Name: anybox.paster.odoo
Version: 1.5
Summary: Paster templates to create an Odoo module or instance using buildout
Home-page: http://anybox.fr
Author: Anybox
Author-email: contact@anybox.fr
License: GPL v3
Keywords: Odoo,paster
Platform: UNKNOWN
